boto3_mfa_cache_patch.pth
boto3_mfa_cache/__init__.py
boto3_mfa_cache-1.0.0.dist-info/licenses/LICENSE
boto3_mfa_cache-1.0.0.dist-info/METADATA
boto3_mfa_cache-1.0.0.dist-info/WHEEL
boto3_mfa_cache-1.0.0.dist-info/top_level.txt
boto3_mfa_cache-1.0.0.dist-info/RECORD
