Metadata-Version: 2.4
Name: boto3-mfa-cache
Version: 1.0.0
Summary: A patch for boto3 to use the AWS CLI credential cache. This uses 
Author: Philip Martin
Requires: boto3
Requires: botocore
License-File: LICENSE
Dynamic: author
Dynamic: description
Dynamic: description-content-type
Dynamic: license-file
Dynamic: requires
Dynamic: summary
